django_redirect_urls-1.0.dist-info/LICENSE.txt
django_redirect_urls-1.0.dist-info/METADATA
django_redirect_urls-1.0.dist-info/RECORD
django_redirect_urls-1.0.dist-info/WHEEL
django_redirect_urls-1.0.dist-info/top_level.txt
redirect_urls/__init__.py
redirect_urls/apps.py
redirect_urls/decorators.py
redirect_urls/middleware.py
redirect_urls/models.py
redirect_urls/utils.py
