Metadata-Version: 2.1
Name: django-redirect-urls
Version: 1.0
Summary: URL redirecting and rewriting in code.
Home-page: https://github.com/pmac/django-redirect-urls/
Author: Paul McLanahan
Author-email: pmac@mozilla.com
License: Apache-2.0
Keywords: django redirects
Platform: UNKNOWN
Classifier: Development Status :: 5 - Production/Stable
Classifier: Framework :: Django
Classifier: Intended Audience :: Developers
Classifier: License :: OSI Approved :: Apache Software License
Classifier: Operating System :: OS Independent
Classifier: Programming Language :: Python
Classifier: Programming Language :: Python :: 2
Classifier: Programming Language :: Python :: 2.7
Classifier: Programming Language :: Python :: 3
Classifier: Programming Language :: Python :: 3.4
Classifier: Programming Language :: Python :: 3.5
Classifier: Programming Language :: Python :: 3.6
Classifier: Topic :: Software Development :: Libraries :: Python Modules
Requires-Dist: Django (>=1.11)
